{
  "name1": "methyltrioctylammonium 1,1,1-trifluoro-N-[(trifluoromethyl)sulfonyl]methanesulfonamide",
  "smi1": "CCCCCCCC[N+](C)(CCCCCCCC)CCCCCCCC.O=S(=O)([N-]S(=O)(=O)C(F)(F)F)C(F)(F)F",
  "name2": "water",
  "smi2": "O",
  "doi": "10.1524/zpch.2013.0328",
  "mixture_data": [
    {
      "measurement": "density",
      "units": "kg/m**3",
      "temperature": {
        "value": 298.15,
        "unit": "K"
      },
      "pressure": {
        "value": 100.0,
        "unit": "kPa"
      },
      "xtype": "mass fraction",
      "x1": [
        0.995
      ],
      "values": [
        1107.2
      ]
    },
    {
      "measurement": "density",
      "units": "kg/m**3",
      "temperature": {
        "value": 303.15,
        "unit": "K"
      },
      "pressure": {
        "value": 100.0,
        "unit": "kPa"
      },
      "xtype": "mass fraction",
      "x1": [
        0.995
      ],
      "values": [
        1103.0
      ]
    },
    {
      "measurement": "density",
      "units": "kg/m**3",
      "temperature": {
        "value": 313.15,
        "unit": "K"
      },
      "pressure": {
        "value": 100.0,
        "unit": "kPa"
      },
      "xtype": "mass fraction",
      "x1": [
        0.995
      ],
      "values": [
        1096.0
      ]
    },
    {
      "measurement": "density",
      "units": "kg/m**3",
      "temperature": {
        "value": 323.15,
        "unit": "K"
      },
      "pressure": {
        "value": 100.0,
        "unit": "kPa"
      },
      "xtype": "mass fraction",
      "x1": [
        0.995
      ],
      "values": [
        1088.5
      ]
    },
    {
      "measurement": "density",
      "units": "kg/m**3",
      "temperature": {
        "value": 333.15,
        "unit": "K"
      },
      "pressure": {
        "value": 100.0,
        "unit": "kPa"
      },
      "xtype": "mass fraction",
      "x1": [
        0.995
      ],
      "values": [
        1081.2
      ]
    },
    {
      "measurement": "density",
      "units": "kg/m**3",
      "temperature": {
        "value": 343.15,
        "unit": "K"
      },
      "pressure": {
        "value": 100.0,
        "unit": "kPa"
      },
      "xtype": "mass fraction",
      "x1": [
        0.995
      ],
      "values": [
        1073.8
      ]
    },
    {
      "measurement": "density",
      "units": "kg/m**3",
      "temperature": {
        "value": 353.15,
        "unit": "K"
      },
      "pressure": {
        "value": 100.0,
        "unit": "kPa"
      },
      "xtype": "mass fraction",
      "x1": [
        0.995
      ],
      "values": [
        1066.5
      ]
    },
    {
      "measurement": "viscosity",
      "units": "Pa•s",
      "temperature": {
        "value": 298.15,
        "unit": "K"
      },
      "pressure": {
        "value": 100.0,
        "unit": "kPa"
      },
      "xtype": "mass fraction",
      "x1": [
        0.995
      ],
      "values": [
        0.601
      ]
    },
    {
      "measurement": "viscosity",
      "units": "Pa•s",
      "temperature": {
        "value": 303.15,
        "unit": "K"
      },
      "pressure": {
        "value": 100.0,
        "unit": "kPa"
      },
      "xtype": "mass fraction",
      "x1": [
        0.995
      ],
      "values": [
        0.426
      ]
    },
    {
      "measurement": "viscosity",
      "units": "Pa•s",
      "temperature": {
        "value": 313.15,
        "unit": "K"
      },
      "pressure": {
        "value": 100.0,
        "unit": "kPa"
      },
      "xtype": "mass fraction",
      "x1": [
        0.995
      ],
      "values": [
        0.239
      ]
    },
    {
      "measurement": "viscosity",
      "units": "Pa•s",
      "temperature": {
        "value": 323.15,
        "unit": "K"
      },
      "pressure": {
        "value": 100.0,
        "unit": "kPa"
      },
      "xtype": "mass fraction",
      "x1": [
        0.995
      ],
      "values": [
        0.144
      ]
    },
    {
      "measurement": "viscosity",
      "units": "Pa•s",
      "temperature": {
        "value": 333.15,
        "unit": "K"
      },
      "pressure": {
        "value": 100.0,
        "unit": "kPa"
      },
      "xtype": "mass fraction",
      "x1": [
        0.995
      ],
      "values": [
        0.092
      ]
    },
    {
      "measurement": "viscosity",
      "units": "Pa•s",
      "temperature": {
        "value": 343.15,
        "unit": "K"
      },
      "pressure": {
        "value": 100.0,
        "unit": "kPa"
      },
      "xtype": "mass fraction",
      "x1": [
        0.995
      ],
      "values": [
        0.065
      ]
    },
    {
      "measurement": "viscosity",
      "units": "Pa•s",
      "temperature": {
        "value": 353.15,
        "unit": "K"
      },
      "pressure": {
        "value": 100.0,
        "unit": "kPa"
      },
      "xtype": "mass fraction",
      "x1": [
        0.995
      ],
      "values": [
        0.046
      ]
    }
  ],
  "pure_compound_data": null
}