{
  "name1": "methanol",
  "smi1": "CO",
  "name2": "1-butyl-3-methylimidazolium thiocyanate",
  "smi2": "CCCC[n+]1ccn(C)c1.N#C[S-]",
  "doi": "10.1016/j.molliq.2015.07.073",
  "mixture_data": [
    {
      "measurement": "density",
      "units": "kg/m**3",
      "temperature": {
        "value": 293.15,
        "unit": "K"
      },
      "pressure": {
        "value": 101.0,
        "unit": "kPa"
      },
      "xtype": "mole fraction",
      "x1": [
        1.0,
        0.9833,
        0.9455,
        0.9042,
        0.8543,
        0.7931,
        0.6379,
        0.4922,
        0.3763,
        0.2882,
        0.1943,
        0.0951,
        0.0
      ],
      "values": [
        791.6,
        814.8,
        858.83,
        896.64,
        928.35,
        958.41,
        1004.88,
        1031.29,
        1044.88,
        1053.2,
        1060.4,
        1067.3,
        1072.6
      ]
    },
    {
      "measurement": "density",
      "units": "kg/m**3",
      "temperature": {
        "value": 298.15,
        "unit": "K"
      },
      "pressure": {
        "value": 101.0,
        "unit": "kPa"
      },
      "xtype": "mole fraction",
      "x1": [
        1.0,
        0.9833,
        0.9455,
        0.9042,
        0.8543,
        0.7931,
        0.6379,
        0.4922,
        0.3763,
        0.2882,
        0.1943,
        0.0951,
        0.0
      ],
      "values": [
        786.9,
        810.2,
        854.56,
        892.63,
        924.55,
        954.79,
        1001.55,
        1028.1,
        1041.77,
        1050.2,
        1057.3,
        1064.3,
        1069.7
      ]
    },
    {
      "measurement": "density",
      "units": "kg/m**3",
      "temperature": {
        "value": 303.15,
        "unit": "K"
      },
      "pressure": {
        "value": 101.0,
        "unit": "kPa"
      },
      "xtype": "mole fraction",
      "x1": [
        1.0,
        0.9833,
        0.9455,
        0.9042,
        0.8543,
        0.7931,
        0.6379,
        0.4922,
        0.3763,
        0.2882,
        0.1943,
        0.0951,
        0.0
      ],
      "values": [
        782.2,
        805.6,
        850.29,
        888.62,
        920.74,
        951.17,
        998.21,
        1024.92,
        1038.67,
        1047.1,
        1054.3,
        1061.3,
        1066.8
      ]
    },
    {
      "measurement": "density",
      "units": "kg/m**3",
      "temperature": {
        "value": 308.15,
        "unit": "K"
      },
      "pressure": {
        "value": 101.0,
        "unit": "kPa"
      },
      "xtype": "mole fraction",
      "x1": [
        1.0,
        0.9833,
        0.9455,
        0.9042,
        0.8543,
        0.7931,
        0.6379,
        0.4922,
        0.3763,
        0.2882,
        0.1943,
        0.0951,
        0.0
      ],
      "values": [
        777.4,
        801.0,
        846.02,
        884.61,
        916.94,
        947.55,
        994.88,
        1021.73,
        1035.56,
        1044.1,
        1051.3,
        1058.3,
        1063.8
      ]
    },
    {
      "measurement": "density",
      "units": "kg/m**3",
      "temperature": {
        "value": 313.15,
        "unit": "K"
      },
      "pressure": {
        "value": 101.0,
        "unit": "kPa"
      },
      "xtype": "mole fraction",
      "x1": [
        1.0,
        0.9833,
        0.9455,
        0.9042,
        0.8543,
        0.7931,
        0.6379,
        0.4922,
        0.3763,
        0.2882,
        0.1943,
        0.0951,
        0.0
      ],
      "values": [
        772.7,
        796.4,
        841.8,
        880.6,
        913.13,
        943.93,
        991.54,
        1018.55,
        1032.46,
        1041.0,
        1048.3,
        1055.4,
        1060.9
      ]
    },
    {
      "measurement": "density",
      "units": "kg/m**3",
      "temperature": {
        "value": 318.15,
        "unit": "K"
      },
      "pressure": {
        "value": 101.0,
        "unit": "kPa"
      },
      "xtype": "mole fraction",
      "x1": [
        1.0,
        0.9833,
        0.9455,
        0.9042,
        0.8543,
        0.7931,
        0.6379,
        0.4922,
        0.3763,
        0.2882,
        0.1943,
        0.0951,
        0.0
      ],
      "values": [
        767.9,
        791.8,
        837.5,
        876.59,
        909.33,
        940.31,
        988.21,
        1015.36,
        1029.35,
        1037.9,
        1045.3,
        1052.4,
        1057.9
      ]
    },
    {
      "measurement": "density",
      "units": "kg/m**3",
      "temperature": {
        "value": 323.15,
        "unit": "K"
      },
      "pressure": {
        "value": 101.0,
        "unit": "kPa"
      },
      "xtype": "mole fraction",
      "x1": [
        1.0,
        0.9833,
        0.9455,
        0.9042,
        0.8543,
        0.7931,
        0.6379,
        0.4922,
        0.3763,
        0.2882,
        0.1943,
        0.0951,
        0.0
      ],
      "values": [
        763.1,
        787.2,
        833.2,
        872.58,
        905.52,
        936.69,
        984.87,
        1012.18,
        1026.25,
        1034.9,
        1042.3,
        1049.4,
        1055.0
      ]
    }
  ],
  "pure_compound_data": null
}