{
  "name1": "Trioctylamine",
  "name2": "p-Xylene",
  "smi1": "CCCCCCCCN(CCCCCCCC)CCCCCCCC",
  "smi2": "Cc1ccc(C)cc1",
  "doi": "10.1021/je9601671",
  "mixture_data": [
    {
      "measurement": "density",
      "units": "g/cm^3",
      "temperature": 298.15,
      "xtype": "mole fraction",
      "x1": [
        0.0000,
        0.0869,
        0.1762,
        0.2683,
        0.3627,
        0.4607,
        0.5627,
        0.6650,
        0.7195,
        0.7744,
        0.8267,
        1.0000
      ],
      "values": [
        0.85661,
        0.84372,
        0.83473,
        0.82813,
        0.82307,
        0.81902,
        0.81570,
        0.81301,
        0.81179,
        0.81066,
        0.80968,
        0.80686
      ]
    }
  ]
}
